Workbook

Sheet Pivot
A1: adapter_code | B1: TSGTATPCLOUDDB_CONN
A2: TSGTAtpCloudDB_Conn
A3: Integration Names / Invoke | B3: Description
A4: TSGTCmnARErpOrchestratorIbFwk_Service | B4: =VLOOKUP(A4,IntegrationsNames!B1:D199,3,FALSE) -> This integration will call procedure to generate FBDI to Obj storage; get FBDI from Obj storage and call ERP Integration Service
A5: TSGTCmnErpDataSyncDispatcherObFwk_Service | B5: =VLOOKUP(A5,IntegrationsNames!B2:D200,3,FALSE) -> Picks up the file from Object Storage and insert into FND_OB_STG table.
A6: TSGTCmnErpDispatcherDataInsertObFwk_Service | B6: =VLOOKUP(A6,IntegrationsNames!B3:D201,3,FALSE) -> Data insert service to OB_STG table
A7: TSGTCmnErpMediatorDataInsertIbFwk_Service | B7: =VLOOKUP(A7,IntegrationsNames!B4:D202,3,FALSE) -> Inbound Framework Service: Read and insert to the stage table; This service will called from the Inbound Mediator service. process : Download from SFTP. Read the file. Enrich the file ;Insert to DB table and send the response.
A8: TSGTCmnErpMediatorIbFwk_Service | B8: =VLOOKUP(A8,IntegrationsNames!B5:D203,3,FALSE) -> This Mediator Service validates and enrich the input file; prepares the FBDI format data and sends the data to Orchestrator Service
A9: TSGTInvErpOnHandDataSyncDispatcherObFwk_Service | B9: =VLOOKUP(A9,IntegrationsNames!B6:D204,3,FALSE) -> Picks up the file from Object Storage and insert into FND_OB_STG table.
A10: TSGTInvOnHandReconOrchestratorIbFwk_Service | B10: =VLOOKUP(A10,IntegrationsNames!B7:D205,3,FALSE) -> This integration will call procedure to compare Erp and WACS OnHand Item Quantities and generate the reconciliation report
A11: TSGTInvWacsOnHandMediatorDataInsertIbFwk_Service | B11: =VLOOKUP(A11,IntegrationsNames!B8:D206,3,FALSE) -> Inventory OnHand Service: Read and insert to the stage table; This service will called from the Inbound Mediator service. process : Download from SFTP. Read the file. Insert to DB table and send the response.
A12: TSGTMingenCheckRunStatus_Service | B12: =VLOOKUP(A12,IntegrationsNames!B9:D207,3,FALSE) -> Integration Identifier: INTE109;** This Interface checks the status of Mingen Report. If Mingen Report is completed; then this interface returns the Success Status along with the Report Sftp Server Path and the Object Storage link as well.
A13: TSGTMingenErpIbInit_Service | B13: =VLOOKUP(A13,IntegrationsNames!B10:D208,3,FALSE) -> Integration Identifier: INTE109;** Integration will trigger the TSGTCmnLauncherFwk_Service to generate the Mingen Report and send the report as attachment in the email and also post it to sftp.
A14: TSGTMingenErpIbReport_Service | B14: =VLOOKUP(A14,IntegrationsNames!B11:D209,3,FALSE) -> Integration Identifier: INTE109;** Integration will generate the Mingen Report and Based on Delivery Mode sends the report as attachment in the email; post it to SFTP; Stores in Object Storage.
A15: TSGTMingenErpLockControl_Service | B15: =VLOOKUP(A15,IntegrationsNames!B12:D210,3,FALSE) -> This integration controls the lock in the TSGT_MINGEN_LOCK_TBL
... A19: Grand Total | B19: =VLOOKUP(A19,IntegrationsNames!B16:D214,3,FALSE) -> #N/A
B20: =VLOOKUP(A20,IntegrationsNames!B17:D215,3,FALSE) -> #N/A
B21: =VLOOKUP(A21,IntegrationsNames!B18:D216,3,FALSE) -> #N/A
B22: =VLOOKUP(A22,IntegrationsNames!B19:D217,3,FALSE) -> #N/A
B23: =VLOOKUP(A23,IntegrationsNames!B20:D218,3,FALSE) -> #N/A
B24: =VLOOKUP(A24,IntegrationsNames!B21:D219,3,FALSE) -> #N/A
B25: =VLOOKUP(A25,IntegrationsNames!B22:D220,3,FALSE) -> #N/A
B26: =VLOOKUP(A26,IntegrationsNames!B23:D221,3,FALSE) -> #N/A
B27: =VLOOKUP(A27,IntegrationsNames!B24:D222,3,FALSE) -> #N/A
B28: =VLOOKUP(A28,IntegrationsNames!B25:D223,3,FALSE) -> #N/A
B29: =VLOOKUP(A29,IntegrationsNames!B26:D224,3,FALSE) -> #N/A
B30: =VLOOKUP(A30,IntegrationsNames!B27:D225,3,FALSE) -> #N/A
B31: =VLOOKUP(A31,IntegrationsNames!B28:D226,3,FALSE) -> #N/A
... B60: =VLOOKUP(A60,IntegrationsNames!B57:D255,3,FALSE) -> #N/A

Sheet IntegrationsNames
A1: id | B1: name | C1: version | D1: description
A2: FA_TAX_EPM_FTP|01.00.0001 | B2: FA_TAX_EPM_Monthly_TAX_LOAD | C2: 01.00.0001 | D2: https://www.oracle.com/pls/topic/lookup?ctx=en/cloud/paas/integration-cloud&id=INTRA-GUID-721BB0DB-5073-4560-8128-3881B460B4EC
A3: FA_TAX_EPM_LOC_CAT_LOAD|01.00.0001 | B3: FA_TAX_EPM_LOC-CAT_LOAD | C3: 01.00.0001 | D3: https://www.oracle.com/pls/topic/lookup?ctx=en/cloud/paas/integration-cloud&id=INTRA-GUID-721BB0DB-5073-4560-8128-3881B460B4EC
A4: FTP_HCM_EPM_FILE_UPLOA_PROJE|01.00.0001 | B4: FTP HCM EPM File Upload_Projects | C4: 01.00.0001 | D4: https://www.oracle.com/pls/topic/lookup?ctx=en/cloud/paas/integration-cloud&id=INTRA-GUID-721BB0DB-5073-4560-8128-3881B460B4EC
A5: FTP_HCM_EPM_FILE_UPLOAD|01.00.0001 | B5: FTP HCM EPM File Upload | C5: 01.00.0001 | D5: https://www.oracle.com/pls/topic/lookup?ctx=en/cloud/paas/integration-cloud&id=INTRA-GUID-721BB0DB-5073-4560-8128-3881B460B4EC
A6: FTP_PPM_EPM_FILE_UPLOAD|01.00.0001 | B6: FTP PPM EPM File Upload | C6: 01.00.0001 | D6: https://www.oracle.com/pls/topic/lookup?ctx=en/cloud/paas/integration-cloud&id=INTRA-GUID-721BB0DB-5073-4560-8128-3881B460B4EC
A7: OUTL-BA-FPRC_WACS_BC_SYNC|01.22.3000 | B7: Oracle Utilities FPRC WACS Blanket Contracts Sync | C7: 01.22.3000 | D7: Syncs Blanket Contracts from Oracle Procurement Cloud(FPRC) to Work and Asset Cloud Service (WACS). This integration is used for both initial load and incremental update sync of Blanket Contract Information.
A8: OUTL-BA-FPRC_WACS_VEND_LOC_SYNC|01.22.3000 | B8: Oracle Utilities FPRC WACS Vendor Locations Sync | C8: 01.22.3000 | D8: Integration flow to sync Vendor Locations from Oracle Procurement Cloud to WACS
A9: OUTL-BA-OFSC_WACS_ACTIVITY_STAT|01.22.3000 | B9: Oracle Utilities OFSC WACS Activity Interim Status | C9: 01.22.3000 | D9: Sends Activity status from OFSC to WAM.
A10: OUTL-BA-OFSC_WACS_ASSET_QUERY|01.22.3000 | B10: Oracle Utilities OFSC WACS Asset Query | C10: 01.22.3000 | D10: This integration flow queries the asset information from WACS.
A11: OUTL-BA-OFSC_WACS_STOREROOM_SYNC|01.22.3000 | B11: Oracle Utilities OFSC WACS Storeroom Sync | C11: 01.22.3000 | D11: This integration flow syncs/update truck storeroom inventory data from WAM to OFSC
A12: OUTL-BA-OFSC_WACS_WORK_REQ|01.22.3000 | B12: Oracle Utilities OFSC WACS Work Request | C12: 01.22.3000 | D12: This flow creates the Work request from OFSC to WACS
... A67: TSGTAUDITINGPROC_SERVICE|01.02.0002 | B67: TSGTAuditingProcess_Service | C67: 01.02.0002 | D67: V1.2.2 - Global Catch log execute message;V1.2.1 - default Body values if not present;V1.2.0 - Added OIC Service Instance in email message
A68: TSGTAZUREADEMPLOYEESOUTBOUNDHCM|02.03.0000 | B68: TSGTAzureADEmployeesOutboundHCM | C68: 02.03.0000
A69: TSGTCMNAPPCOMPOS_SERVICE|01.00.0000 | B69: TSGTCmnAppComposerObjUpdate_Service | C69: 01.00.0000
A70: TSGTCMNARERPORCH_SERVICE|01.00.0000 | B70: TSGTCmnARErpOrchestratorIbFwk_Service | C70: 01.00.0000 | D70: This integration will call procedure to generate FBDI to Obj storage; get FBDI from Obj storage and call ERP Integration Service
A71: TSGTCMNCHECKESSJOBSTATUS_SERVICE|01.00.0000 | B71: TSGTCmnCheckESSJOBStatus_Service | C71: 01.00.0000 | D71: Utility Service: This Integration Service will get the ESS Process Id and Invoke the SOAP Service to receive the ESS Job Status [SUCCESS/ERROR/TIMEOUT].
A72: TSGTCMNERPCALLBA_SERVICE|01.00.0000 | B72: TSGTCmnErpCallbackObFwk_Service | C72: 01.00.0000 | D72: Common framework to receive callback for Outbound ESS Jobs from Oracle fusion application
A73: TSGTCMNERPCALLBACKIBFWK_SERVICE|01.00.0000 | B73: TSGTCmnErpCallbackIbFwk_Service | C73: 01.00.0000 | D73: Common Inbound framework to receive callback from Oracle fusion application
A74: TSGTCMNERPDATASY_SERVICE|01.00.0000 | B74: TSGTCmnErpDataSyncDispatcherObFwk_Service | C74: 01.00.0000 | D74: Picks up the file from Object Storage and insert into FND_OB_STG table.
A75: TSGTCMNERPDISPAT_SERVICE|01.00.0000 | B75: TSGTCmnErpDispatcherDataInsertObFwk_Service | C75: 01.00.0000 | D75: Data insert service to OB_STG table
A76: TSGTCMNERPLAUNCH_SERVICE_OB|01.00.0000 | B76: TSGTCmnErpLauncherObFwk_Service | C76: 01.00.0000 | D76: Common Framework Outbound Integration will Submit Custom ESS Job in SaaS which will upload the Output Extract to UCM.
A77: TSGTCMNERPLAUNCH_SERVICE|01.00.0000 | B77: TSGTCmnErpLauncherIbFwk_Service | C77: 01.00.0000 | D77: Common Launcher to trigger ERP Integrations
A78: TSGTCMNERPMEDIATDATAINSER_SERVIC|01.00.0000 | B78: TSGTCmnErpMediatorDataInsertIbFwk_Service | C78: 01.00.0000 | D78: Inbound Framework Service: Read and insert to the stage table; This service will called from the Inbound Mediator service. process : Download from SFTP. Read the file. Enrich the file ;Insert to DB table and send the response.
A79: TSGTCMNERPMEDIATORIBFWK_SERVICE|01.00.0000 | B79: TSGTCmnErpMediatorIbFwk_Service | C79: 01.00.0000 | D79: This Mediator Service validates and enrich the input file; prepares the FBDI format data and sends the data to Orchestrator Service
A80: TSGTCMNERPSFTPDISPOBFWK_SERVICE|01.00.0000 | B80: TSGTCmnErpSftpDispatcherObFwk_Service | C80: 01.00.0000 | D80: Common framework to transfer file from Object Storage to SFTP for Outbound Integration
A81: TSGTCMNFILEREFER_SERVICE|01.00.0000 | B81: TSGTCmnFileReferencetoObjectStorage_Service | C81: 01.00.0000 | D81: This Interface moves the file reference (Base64 encoded from) to the object storage.
... A83: TSGTCMNGETESSLOGOUT_SERVICE|01.00.0000 | B83: TSGTCmnGetEssLogOutput_Service | C83: 01.00.0000 | D83: This Integration extracts the Log and Output Files of an ESS Job
A84: TSGTCMNHCMDISPAT_SERVICE|01.00.0000 | B84: TSGTCmnHcmDispatcher_Service | C84: 01.00.0000
A85: TSGTCMNHCMDISPAT_SERVICE|02.00.0001 | B85: TSGTCmnHcmDispatcher_Service | C85: 02.00.0001 | D85: V2.0 - Remove encryption for SailPoint;V1.2 - SailPoint route only SailPoint target system;- COBRA added ;V1.0.0 servers VSP; EPM; SNAP; HSA; Kaiser; DeltaDental
A86: TSGTCMNHCMEXTRAC_SERVICE|01.00.0000 | B86: TSGTCmnHcmExtractProcess_Service | C86: 01.00.0000
A87: TSGTCMNHCMINBOUN_SERVICE|01.00.0000 | B87: TSGTCmnHcmInboundProcess_Service | C87: 01.00.0000
A88: TSGTCMNHCMLAUNCH_SERVICE|01.00.0000 | B88: TSGTCmnHcmLauncherFwk_Service | C88: 01.00.0000
A89: TSGTCMNHCMNOTIFI_SERVICE|01.00.0000 | B89: TSGTCmnHcmNotification_Service | C89: 01.00.0000
A90: TSGTCMNLAUNCHERF_SERVICE|01.00.0000 | B90: TSGTCmnLauncherFwk_Service | C90: 01.00.0000 | D90: Integration that is kicked-off from the Adhoc submission UI screen
A91: TSGTCMNNOTIFICAT_SERVICE|01.00.0000 | B91: TSGTCmnNotificationFwk_Service | C91: 01.00.0000 | D91: Generic notification service call from the Inbound and outbound integrations
A92: TSGTCMNOBJECTSTOSFTPMOVE_SERVICE|01.00.0000 | B92: TSGTCmnObjectStorageToSFTPMove_Service | C92: 01.00.0000 | D92: This Interface moves the file from object storage to the different sftp path.
A93: TSGTCMNOBJSTRGFI_SERVICE|01.00.0000 | B93: TSGTCmnObjStrgFileDownload_Service | C93: 01.00.0000 | D93: Integration to download files from Object storage buckets
A94: TSGTCMNOBJSTRGFILE_SERVICE|01.00.0000 | B94: TSGTCmnObjStrgFile_Service | C94: 01.00.0000 | D94: Find/Delete file in object storage
A95: TSGTCMNOBJSTRGPU_SERVICE|01.00.0000 | B95: TSGTCmnObjStrgPurge_Service | C95: 01.00.0000 | D95: To Purge the Object Storage Files
A96: TSGTCMNPURGEOS_INTGSERVICE|01.00.0000 | B96: TSGTCmnPurgeOS_IntgService | C96: 01.00.0000 | D96: Common Purge Object Storage - wrapper service
A97: TSGTCMNPURGESFTP_INTGSERVICE|01.00.0000 | B97: TSGTCmnPurgeSFTP_IntgService | C97: 01.00.0000 | D97: Common Purge SFTP - wrapper service
A98: TSGTCMNREPROCESS_SERVICE|01.00.0000 | B98: TSGTCmnReprocess_Service | C98: 01.00.0000 | D98: Common integration to republish the Outbound files to respective dispatcher
A99: TSGTCMNREPUBLISH_SERVICE|01.00.0000 | B99: TSGTCmnRepublish_Service | C99: 01.00.0000 | D99: Common integration to republish the Outbound files to respective dispatcher
A100: TSGTCMNRESENDPRO_SERVICE|01.00.0000 | B100: TSGTCmnResendProcessingResults_Service | C100: 01.00.0000
A101: TSGTCMNSENDESSLOGOUTPUTEMAIL|01.00.0000 | B101: TSGTCmnSendESSLogOutputEmail | C101: 01.00.0000 | D101: This Integration extracts the Log and Output Files of an ESS Job
A102: TSGTCMNSFTPFILEO_SERVICE|01.00.0000 | B102: TSGTCmnSFTPFileOperation_Service | C102: 01.00.0000 | D102: This Interface moves Documents from Source sftp path to target SFTP
A103: TSGTCMNSFTPPURGE_SERVICE|01.00.0000 | B103: TSGTCmnSFTPPurge_Service | C103: 01.00.0000 | D103: To Purge the SFTP Files
A104: TSGTCMNSFTPTOOBJSTORAGEMOV_SERVI|01.00.0000 | B104: TSGTCmnSFTPtoObjectStorageMove_Service | C104: 01.00.0000 | D104: This Interface moves the file from sftp path to the object storage.
A105: TSGTCMNSRCOBJSTOTGTOBJSMO_SERVIC|01.00.0000 | B105: TSGTCmnSrcObjStorageToTgtObjStorageMove_Service | C105: 01.00.0000 | D105: This Interface moves the file from source object storage bucket to the target object storage bucket.
A106: TSGTCMNUCMTOOBJEMOVE_SERVICE|01.00.0000 | B106: TSGTCmnUCMToObjectStorageMove_Service | C106: 01.00.0000 | D106: This Interface moves the UCM files to corresponding object storage.
A107: TSGTCMNUCMTOSFTP_SERVICE|01.00.0000 | B107: TSGTCmnUCMtoSFTPMove_Service | C107: 01.00.0000 | D107: This Interface moves the UCM files to corresponding sftp path.
A108: TSGTCMNUPSERTINS_SERVICE|01.00.0000 | B108: TSGTCmnUpsertInstanceTransaction_Service | C108: 01.00.0000
A109: TSGTCMNUTILFILEU_SERVICE|01.00.0001 | B109: TSGTCmnUtilFileUpload_Service | C109: 01.00.0001 | D109: Receive Base64 encoded data from VBCS portal and upload file to SFTP directory;.
A110: TSGTCMNWITHPARAM_SERVICE|01.00.0000 | B110: TSGTCmnWithParamIntg_Service | C110: 01.00.0000 | D110: Integration Service to Run the Integrations on Adhoc Basis
A111: TSGTCMNXRE_INTGSERVIC_OB|01.00.0000 | B111: TSGTCmnXrefExtract_IntgService_OB | C111: 01.00.0000
A112: TSGTEMPLOYEEFIDELITYDELIVERY|02.00.0001 | B112: TSGTEmployeeFidelityDelivery | C112: 02.00.0001 | D112: V2.0.1-bugfix-dont' send email anymore when no employees
A113: TSGTEMPLOYEESBCPPROCESS|02.00.0000 | B113: TSGTEmployeesBCPProcess | C113: 02.00.0000
A114: TSGTEMPLOYEESBENEFITHUBPROCESS|02.00.0000 | B114: TSGTEmployeesBenefithubProcess | C114: 02.00.0000
A115: TSGTEMPLOYEESCOLLECTIVEVIEW|02.00.0000 | B115: TSGTEmployeesCollectiveView | C115: 02.00.0000 | D115: Submits Employee Info HCM extract and places the output file in SFTP server
A116: TSGTEMPLOYEESCORITYPROCESS|02.06.0000 | B116: TSGTEmployeesCorityProcess | C116: 02.06.0000
A117: TSGTEMPLOYEESEBSPROCESS|02.00.0000 | B117: TSGTEmployeesEBSProcess | C117: 02.00.0000
A118: TSGTEMPLOYEESFIDELITYPROCESS|02.01.0000 | B118: TSGTEmployeesFidelityProcess | C118: 02.01.0000
A119: TSGTEMPLOYEESFLIGHTTRAKPROCESS|02.00.0000 | B119: TSGTEmployeesFlightTrakProcess | C119: 02.00.0000
A120: TSGTEMPLOYEESPHONESPROCESS|01.01.0000 | B120: TSGTEmployeesPhonesProcess | C120: 01.01.0000
A121: TSGTEMPLOYEESSNAPPROCESS|02.00.0000 | B121: TSGTEmployeesSnapProcess | C121: 02.00.0000
A122: TSGTEMPLOYEESUNUMPROCESS|02.00.0000 | B122: TSGTEmployeesUNUMProcess | C122: 02.00.0000
A123: TSGTEMPLOYEESVEOCIPROCESS|02.05.0000 | B123: TSGTEmployeesVeociProcess | C123: 02.05.0000
A124: TSGTFAASSET_INTGSERVIC_OB|01.00.0000 | B124: TSGTFAAssetNumberUpdatetoWACS_IntgService_OB | C124: 01.00.0000 | D124: Integration Identifier: INTE02A-FA_ASSET_NUMBER_UPDATE_WACS;** Integration will trigger the Common Launcher Service to extract the FA Asset Number and WACS Asset Number
A125: TSGTFANUMBERUPDA_SERVICE|01.00.0000 | B125: TSGTFANumberUpdatetoWACSDispatcher_Service | C125: 01.00.0000 | D125: Picks up the file from Object Storage and update the FA Asset Number in WACS
A126: TSGTFILERETENTIONCHECK|01.00.0000 | B126: TSGTFileRetentionCheck | C126: 01.00.0000 | D126: Service that converts epoch time to Converted Date and delete file from sftp if file is greater then rention period
A127: TSGTFLIGHT_INTGSERVIC_IB|01.00.0000 | B127: TSGTFlightMiscCostImport_IntgService_IB | C127: 01.00.0000 | D127: Integration Identifier: INTE94-Flight Misc Cost Import; ** Integration will trigger the Common Launcher Service to import flight miscellaneous cost.**
A128: TSGTGETCONFIGS_SERVICE|01.02.0000 | B128: TSGTGetConfigs_Service | C128: 01.02.0000
A129: TSGTHAZARDITEMEXTR_INTGSERVIC_OB|01.00.0000 | B129: TSGTHazardousItemExtract_IntgService_OB | C129: 01.00.0000 | D129: Integration Identifier: INTE53;** Integration will trigger the Common Launcher Service to extract Hazardous Items from cloud and process the extracts through a file to the sftp path.
A130: TSGTHCMASSIGNMENTUPDATEBYPUBLISH|01.01.0000 | B130: TSGTHCMAssignmentUpdateByPublish | C130: 01.01.0000
A131: TSGTHCMASSIGNMENTUPDATEBYPUBLISH|02.00.0000 | B131: TSGTHCMAssignmentUpdateByPublish | C131: 02.00.0000
A132: TSGTHCMASSIGNMENTUPDATEBYUPDATE|01.01.0000 | B132: TSGTHCMAssignmentUpdateByUpdate | C132: 01.01.0000
A133: TSGTHCMASSIGNMENTUPDATEBYUPDATE|02.00.0000 | B133: TSGTHCMAssignmentUpdateByUpdate | C133: 02.00.0000
A134: TSGTHCMDAILYPROCESS|02.00.0000 | B134: TSGTHCMDailyProcess | C134: 02.00.0000
A135: TSGTHCMEMPLOYEESEXTRACT|02.00.0000 | B135: TSGTHCMEmployeesExtract | C135: 02.00.0000
A136: TSGTHCMEMPLOYEESTERMINATION|02.00.0000 | B136: TSGTHCMEmployeesTermination | C136: 02.00.0000
A137: TSGTHCMEMPLOYEESUPDATEOUTBOUND|01.02.0000 | B137: TSGTHCMEmployeesUpdateOutbound | C137: 01.02.0000
A138: TSGTHCMEMPLOYEESUPDATEOUTBOUND|02.00.0001 | B138: TSGTHCMEmployeesUpdateOutbound | C138: 02.00.0001
A139: TSGTHCMEMPLOYEETERMINATIONBYUPDA|01.01.0000 | B139: TSGTHCMEmployeeTerminationByUpdate | C139: 01.01.0000
A140: TSGTHCMEMPLOYEETERMINATIONBYUPDA|02.00.0000 | B140: TSGTHCMEmployeeTerminationByUpdate | C140: 02.00.0000
A141: TSGTHCMEXTRACTLOADER|01.00.0000 | B141: TSGTHCMExtractLoader | C141: 01.00.0000
... A146: TSGTHCMNEWHIRESOUTBOUNDBYUPDATE|02.00.0001 | B146: TSGTHCMNewHiresOutboundByUpdate | C146: 02.00.0001
A147: TSGTHCMOTLSNAP_SERVICE|01.00.0001 | B147: TSGTHcmOTLSnap_Service | C147: 01.00.0001 | D147: V1.0.0001 - Content-length header added to SNAP API call
A148: TSGTHCMPAYROLLHOURS2CORITY|01.00.0000 | B148: TSGTHCMPayrollHours2Cority | C148: 01.00.0000
A149: TSGTHCMPAYROLLHOURS2CORITY|02.01.0000 | B149: TSGTHCMPayrollHours2Cority | C149: 02.01.0000
A150: TSGTHCMSAASTRANS_SERVICE|01.00.0000 | B150: TSGTHcmSaasTransformation_Service | C150: 01.00.0000
A151: TSGTINVERP_INTGSERVIC_IB|01.00.0000 | B151: TSGTInvErpWACSOnHandRecon_IntgService_IB | C151: 01.00.0000 | D151: Integration Identifier:INTE120 - ERP-WACS Onhand Recon;** Integration will trigger the Common Launcher Service to Compare of onhand quantity from WACS to ERP
A152: TSGTINVERPONHAND_SERVICE|01.00.0000 | B152: TSGTInvErpOnHandDataSyncDispatcherObFwk_Service | C152: 01.00.0000 | D152: Picks up the file from Object Storage and insert into FND_OB_STG table.
A153: TSGTINVOIC_INTGSERVIC_OB|01.00.0000 | B153: TSGTInvoicePaymentExtract_IntgService_OB | C153: 01.00.0000 | D153: Integration Identifier: INTE13-INVOICEPAYMENTEXTRACTTOWACS;** Integration will trigger the Common Launcher Service to extract Invoices with payment details from cloud and process the extracts through a file to the sftp path.
A154: TSGTINVONHANDREC_SERVICE|01.00.0000 | B154: TSGTInvOnHandReconOrchestratorIbFwk_Service | C154: 01.00.0000 | D154: This integration will call procedure to compare Erp and WACS OnHand Item Quantities and generate the reconciliation report
A155: TSGTINVWACSONHAN_SERVICE|01.00.0000 | B155: TSGTInvWacsOnHandMediatorDataInsertIbFwk_Service | C155: 01.00.0000 | D155: Inventory OnHand Service: Read and insert to the stage table; This service will called from the Inbound Mediator service. process : Download from SFTP. Read the file. Insert to DB table and send the response.
A156: TSGTLEADTI_INTGSERVIC_OB|01.00.0000 | B156: TSGTLeadTimeUpdate_IntgService_OB | C156: 01.00.0000 | D156: Integration Identifier: EXT001;** Integration will trigger the Common Launcher Service to extract the processing lead time in item master based on the PO line receipt
A157: TSGTLEADTIMEERPU_SERVICE|01.00.0000 | B157: TSGTLeadTimeERPUpdateDispatcher_Service | C157: 01.00.0000 | D157: Picks up the file from Object Storage and update the lead time of the items in the Oracle ERP using REST API
A158: TSGTLISTPR_INTGSERVIC_OB|01.00.0000 | B158: TSGTListPriceUpdate_IntgService_OB | C158: 01.00.0000 | D158: Integration Identifier: EXT002;** Integration will trigger the Common Launcher Service to extract the total unit cost of the items and update the list price of those items.
A159: TSGTLISTPRICEERP_SERVICE|01.00.0000 | B159: TSGTListPriceERPUpdateDispatcher_Service | C159: 01.00.0000 | D159: Picks up the file from Object Storage and update the list price of the items in the Oracle ERP using REST API
...

Sheet INVOKE-XREF
A1: source_file | B1: source_integration | C1: source_integration_code | D1: source_integration_name | E1: source_integration_version | F1: invoke | G1: call_type | H1: target_integration_code | I1: target_version | J1: target_integration_name | K1: resource_uri | L1: adapter_code | M1: application_name | N1: error
A2: BIP_SCHEDU_REPORT_WSS_SERVIC_01.00.0000.iar.yaml | B2: BIP_SCHEDU_REPORT_WSS_SERVIC 01.00.0000 | C2: BIP_SCHEDU_REPORT_WSS_SERVIC | D2: BIP Schedule Report WSS Service | E2: 01.00.0000 | F2: SubmitScheduleReport(i0) | G2: Adapter_Invoke | L2: BIP_SCHEDULEREPORTWS | M2: SubmitScheduleReport
A3: FA_TAX_EPM_FTP_01.00.0001.iar.yaml | B3: FA_TAX_EPM_FTP 01.00.0001 | C3: FA_TAX_EPM_FTP | D3: FA_TAX_EPM_Monthly_TAX_LOAD | E3: 01.00.0001 | F3: ftp_location(i0) | G3: Adapter_Invoke | L3: ORCL-BRT-FTP_CONN | M3: ftp_location
A4: FA_TAX_EPM_FTP_01.00.0001.iar.yaml | B4: FA_TAX_EPM_FTP 01.00.0001 | C4: FA_TAX_EPM_FTP | D4: FA_TAX_EPM_Monthly_TAX_LOAD | E4: 01.00.0001 | F4: FA_TAX_EPMrestupload(i2) | G4: Adapter_Invoke | K4: /interop/rest/11.1.2.3.600/applicationsnapshots/{file_name}/contents | L4: ORACL_REST_EPM_CONNE_FA_TAX | M4: FA_TAX_EPMrestupload
A5: FA_TAX_EPM_LOC_CAT_LOAD_01.00.0001.iar.yaml | B5: FA_TAX_EPM_LOC_CAT_LOAD 01.00.0001 | C5: FA_TAX_EPM_LOC_CAT_LOAD | D5: FA_TAX_EPM_LOC-CAT_LOAD | E5: 01.00.0001 | F5: ftp_location(i0) | G5: Adapter_Invoke | L5: ORCL-BRT-FTP_CONN | M5: ftp_location
A6: FA_TAX_EPM_LOC_CAT_LOAD_01.00.0001.iar.yaml | B6: FA_TAX_EPM_LOC_CAT_LOAD 01.00.0001 | C6: FA_TAX_EPM_LOC_CAT_LOAD | D6: FA_TAX_EPM_LOC-CAT_LOAD | E6: 01.00.0001 | F6: FA_TAX_EPMrestupload(i2) | G6: Adapter_Invoke | K6: /interop/rest/11.1.2.3.600/applicationsnapshots/{file_name}/contents | L6: ORACL_REST_EPM_CONNE_FA_TAX | M6: FA_TAX_EPMrestupload
A7: FTP_HCM_EPM_FILE_UPLOAD_01.00.0001.iar.yaml | B7: FTP_HCM_EPM_FILE_UPLOAD 01.00.0001 | C7: FTP_HCM_EPM_FILE_UPLOAD | D7: FTP HCM EPM File Upload | E7: 01.00.0001 | F7: ftp_location(i0) | G7: Adapter_Invoke | L7: ORCL-BRT-FTP_CONN | M7: ftp_location
A8: FTP_HCM_EPM_FILE_UPLOAD_01.00.0001.iar.yaml | B8: FTP_HCM_EPM_FILE_UPLOAD 01.00.0001 | C8: FTP_HCM_EPM_FILE_UPLOAD | D8: FTP HCM EPM File Upload | E8: 01.00.0001 | F8: epm_rest_upload(i1) | G8: Adapter_Invoke | K8: /interop/rest/11.1.2.3.600/applicationsnapshots/{file_name}/contents | L8: ORCL-BRT-REST-EPM_CONNECTION | M8: epm_rest_upload
A9: FTP_HCM_EPM_FILE_UPLOA_PROJE_01.00.0001.iar.yaml | B9: FTP_HCM_EPM_FILE_UPLOA_PROJE 01.00.0001 | C9: FTP_HCM_EPM_FILE_UPLOA_PROJE | D9: FTP HCM EPM File Upload_Projects | E9: 01.00.0001 | F9: ftp_location(i0) | G9: Adapter_Invoke | L9: ORCL-BRT-FTP_CONN | M9: ftp_location
A10: FTP_HCM_EPM_FILE_UPLOA_PROJE_01.00.0001.iar.yaml | B10: FTP_HCM_EPM_FILE_UPLOA_PROJE 01.00.0001 | C10: FTP_HCM_EPM_FILE_UPLOA_PROJE | D10: FTP HCM EPM File Upload_Projects | E10: 01.00.0001 | F10: epm_rest_upload(i1) | G10: Adapter_Invoke | K10: /interop/rest/11.1.2.3.600/applicationsnapshots/{file_name}/contents | L10: ORACLE_REST_EPM_CONNEC_PROJEC | M10: epm_rest_upload
A11: FTP_PPM_EPM_FILE_UPLOAD_01.00.0001.iar.yaml | B11: FTP_PPM_EPM_FILE_UPLOAD 01.00.0001 | C11: FTP_PPM_EPM_FILE_UPLOAD | D11: FTP PPM EPM File Upload | E11: 01.00.0001 | F11: ftp_location(i0) | G11: Adapter_Invoke | L11: ORCL-BRT-FTP_CONN | M11: ftp_location
A12: FTP_PPM_EPM_FILE_UPLOAD_01.00.0001.iar.yaml | B12: FTP_PPM_EPM_FILE_UPLOAD 01.00.0001 | C12: FTP_PPM_EPM_FILE_UPLOAD | D12: FTP PPM EPM File Upload | E12: 01.00.0001 | F12: epm_rest_upload(i1) | G12: Adapter_Invoke | K12: /interop/rest/11.1.2.3.600/applicationsnapshots/{file_name}/contents | L12: ORACLE_REST_EPM_CONNEC_PROJEC | M12: epm_rest_upload
A13: GET_SECRET_BY_NAME_01.00.0001.iar.yaml | B13: GET_SECRET_BY_NAME 01.00.0001 | C13: GET_SECRET_BY_NAME | D13: Get Secret By Name | E13: 01.00.0001 | F13: OCI_Secrete_By_Name(i0) | G13: Adapter_Invoke | K13: /20190301/secretbundles/actions/getByName | L13: OCI_VAULT_SECRETS | M13: OCI_Secrete_By_Name
A14: GET_SECRET_BY_NAME_01.00.0001.iar.yaml | B14: GET_SECRET_BY_NAME 01.00.0001 | C14: GET_SECRET_BY_NAME | D14: Get Secret By Name | E14: 01.00.0001 | F14: SendErrorNotification(i1) | G14: IntegrationAction | H14: SEND_EMAIL | I14: 01.00.0001 | J14: Send Email | K14: / | L14: PRESEEDED_COLLOCATED_CONN_1741 | M14: SendErrorNotification
A15: ORAC_UTIL_FPRC_WACS_VEND_LOC__CL_02.22.3001.iar.yaml | B15: ORAC_UTIL_FPRC_WACS_VEND_LOC__CL 02.22.3001 | C15: ORAC_UTIL_FPRC_WACS_VEND_LOC__CL | D15: Oracle Utilities FPRC WACS Vendor Loc -CLEANNER | E15: 02.22.3001 | F15: searchVendorLocationFile(i0) | G15: Adapter_Invoke | L15: OUTL-BRT-SOAP-UCM_WACSFPRC | M15: searchVendorLocationFile
A16: ORAC_UTIL_FPRC_WACS_VEND_LOC__CL_02.22.3001.iar.yaml | B16: ORAC_UTIL_FPRC_WACS_VEND_LOC__CL 02.22.3001 | C16: ORAC_UTIL_FPRC_WACS_VEND_LOC__CL | D16: Oracle Utilities FPRC WACS Vendor Loc -CLEANNER | E16: 02.22.3001 | F16: GetFileFromUCM(i2) | G16: Adapter_Invoke | L16: OUTL-BRT-SOAP-UCM_WACSFPRC | M16: GetFileFromUCM
A17: ORAC_UTIL_FPRC_WACS_VEND_LOC__CL_02.22.3001.iar.yaml | B17: ORAC_UTIL_FPRC_WACS_VEND_LOC__CL 02.22.3001 | C17: ORAC_UTIL_FPRC_WACS_VEND_LOC__CL | D17: Oracle Utilities FPRC WACS Vendor Loc -CLEANNER | E17: 02.22.3001 | F17: Rename_ZipFile_UnzipFault(i5) | G17: Adapter_Invoke | L17: OUTL-BRT-SOAP-UCM_WACSFPRC | M17: Rename_ZipFile_UnzipFault
A18: ORAC_UTIL_FPRC_WACS_VEND_LOC__CL_02.22.3001.iar.yaml | B18: ORAC_UTIL_FPRC_WACS_VEND_LOC__CL 02.22.3001 | C18: ORAC_UTIL_FPRC_WACS_VEND_LOC__CL | D18: Oracle Utilities FPRC WACS Vendor Loc -CLEANNER | E18: 02.22.3001 | F18: renameFileInUCM(i4) | G18: Adapter_Invoke | L18: OUTL-BRT-SOAP-UCM_WACSFPRC | M18: renameFileInUCM
A19: OUTL-BA-FPRC_WACS_BC_SYNC_01.22.3000.iar.yaml | B19: OUTL-BA-FPRC_WACS_BC_SYNC 01.22.3000 | C19: OUTL-BA-FPRC_WACS_BC_SYNC | D19: Oracle Utilities FPRC WACS Blanket Contracts Sync | E19: 01.22.3000 | F19: invokeWACS_HealthCheck(i0) | G19: Adapter_Invoke | K19: https://us-phoenix-1.utilities-cloud.oracleindustry.com:443/c2g65p/prod/wac/rest/apis/common/system/healthCheck/ | L19: OUTL-BRT-REST-WACS_WACSFPRC | M19: invokeWACS_HealthCheck
A20: OUTL-BA-FPRC_WACS_BC_SYNC_01.22.3000.iar.yaml | B20: OUTL-BA-FPRC_WACS_BC_SYNC 01.22.3000 | C20: OUTL-BA-FPRC_WACS_BC_SYNC | D20: Oracle Utilities FPRC WACS Blanket Contracts Sync | E20: 01.22.3000 | F20: searchBlanketContractFile(i1) | G20: Adapter_Invoke | L20: OUTL-BRT-SOAP-UCM_WACSFPRC | M20: searchBlanketContractFile
A21: OUTL-BA-FPRC_WACS_BC_SYNC_01.22.3000.iar.yaml | B21: OUTL-BA-FPRC_WACS_BC_SYNC 01.22.3000 | C21: OUTL-BA-FPRC_WACS_BC_SYNC | D21: Oracle Utilities FPRC WACS Blanket Contracts Sync | E21: 01.22.3000 | F21: GetFileFromUCM(i2) | G21: Adapter_Invoke | L21: OUTL-BRT-SOAP-UCM_WACSFPRC | M21: GetFileFromUCM
A22: OUTL-BA-FPRC_WACS_BC_SYNC_01.22.3000.iar.yaml | B22: OUTL-BA-FPRC_WACS_BC_SYNC 01.22.3000 | C22: OUTL-BA-FPRC_WACS_BC_SYNC | D22: Oracle Utilities FPRC WACS Blanket Contracts Sync | E22: 01.22.3000 | F22: invoke_UOMConversionRest(i5) | G22: Adapter_Invoke | L22: OUTL-BRT-ERPCLOUD_WACSFPRC | M22: invoke_UOMConversionRest
A23: OUTL-BA-FPRC_WACS_BC_SYNC_01.22.3000.iar.yaml | B23: OUTL-BA-FPRC_WACS_BC_SYNC 01.22.3000 | C23: OUTL-BA-FPRC_WACS_BC_SYNC | D23: Oracle Utilities FPRC WACS Blanket Contracts Sync | E23: 01.22.3000 | F23: InvokeWACSBCSync(i6) | G23: Adapter_Invoke | K23: https://us-phoenix-1.utilities-cloud.oracleindustry.com:443/c2g65p/prod/wac/rest/apis/asset/purchasing/blanketContractSynchronization/ | L23: OUTL-BRT-REST-WACS_WACSFPRC | M23: InvokeWACSBCSync
A24: OUTL-BA-FPRC_WACS_BC_SYNC_01.22.3000.iar.yaml | B24: OUTL-BA-FPRC_WACS_BC_SYNC 01.22.3000 | C24: OUTL-BA-FPRC_WACS_BC_SYNC | D24: Oracle Utilities FPRC WACS Blanket Contracts Sync | E24: 01.22.3000 | F24: remaneFileInUCM(i4) | G24: Adapter_Invoke | L24: OUTL-BRT-SOAP-UCM_WACSFPRC | M24: remaneFileInUCM
A25: OUTL-BA-FPRC_WACS_VEND_LOC_SYNC_01.22.3000.iar.yaml | B25: OUTL-BA-FPRC_WACS_VEND_LOC_SYNC 01.22.3000 | C25: OUTL-BA-FPRC_WACS_VEND_LOC_SYNC | D25: Oracle Utilities FPRC WACS Vendor Locations Sync | E25: 01.22.3000 | F25: invokeHealthCheck(i1) | G25: Adapter_Invoke | K25: https://us-phoenix-1.utilities-cloud.oracleindustry.com:443/c2g65p/prod/wac/rest/apis/common/system/healthCheck/ | L25: OUTL-BRT-REST-WACS_WACSFPRC | M25: invokeHealthCheck
A26: OUTL-BA-FPRC_WACS_VEND_LOC_SYNC_01.22.3000.iar.yaml | B26: OUTL-BA-FPRC_WACS_VEND_LOC_SYNC 01.22.3000 | C26: OUTL-BA-FPRC_WACS_VEND_LOC_SYNC | D26: Oracle Utilities FPRC WACS Vendor Locations Sync | E26: 01.22.3000 | F26: searchVendorLocationFile(i0) | G26: Adapter_Invoke | L26: OUTL-BRT-SOAP-UCM_WACSFPRC | M26: searchVendorLocationFile
A27: OUTL-BA-FPRC_WACS_VEND_LOC_SYNC_01.22.3000.iar.yaml | B27: OUTL-BA-FPRC_WACS_VEND_LOC_SYNC 01.22.3000 | C27: OUTL-BA-FPRC_WACS_VEND_LOC_SYNC | D27: Oracle Utilities FPRC WACS Vendor Locations Sync | E27: 01.22.3000 | F27: GetFileFromUCM(i2) | G27: Adapter_Invoke | L27: OUTL-BRT-SOAP-UCM_WACSFPRC | M27: GetFileFromUCM
A28: OUTL-BA-FPRC_WACS_VEND_LOC_SYNC_01.22.3000.iar.yaml | B28: OUTL-BA-FPRC_WACS_VEND_LOC_SYNC 01.22.3000 | C28: OUTL-BA-FPRC_WACS_VEND_LOC_SYNC | D28: Oracle Utilities FPRC WACS Vendor Locations Sync | E28: 01.22.3000 | F28: InvokeWACSVendorLocSync(i3) | G28: Adapter_Invoke | K28: https://us-phoenix-1.utilities-cloud.oracleindustry.com:443/c2g65p/prod/wac/rest/apis/asset/purchasing/vendorLocationSynchronization/ | L28: OUTL-BRT-REST-WACS_WACSFPRC | M28: InvokeWACSVendorLocSync
A29: OUTL-BA-FPRC_WACS_VEND_LOC_SYNC_01.22.3000.iar.yaml | B29: OUTL-BA-FPRC_WACS_VEND_LOC_SYNC 01.22.3000 | C29: OUTL-BA-FPRC_WACS_VEND_LOC_SYNC | D29: Oracle Utilities FPRC WACS Vendor Locations Sync | E29: 01.22.3000 | F29: renameFileInUCM(i4) | G29: Adapter_Invoke | L29: OUTL-BRT-SOAP-UCM_WACSFPRC | M29: renameFileInUCM
A30: OUTL-BA-OFSC_WACS_ACTIVITY_STAT_01.22.3000.iar.yaml | B30: OUTL-BA-OFSC_WACS_ACTIVITY_STAT 01.22.3000 | C30: OUTL-BA-OFSC_WACS_ACTIVITY_STAT | D30: Oracle Utilities OFSC WACS Activity Interim Status | E30: 01.22.3000 | F30: getActivityDetails(i1) | G30: Adapter_Invoke | K30: https://tsgt.fs.ocs.oraclecloud.com/rest/ofscCore/v1/activities/{activityId} | L30: OUTL-BRT-APP-OFSC_WACSOFSC | M30: getActivityDetails
A31: OUTL-BA-OFSC_WACS_ACTIVITY_STAT_01.22.3000.iar.yaml | B31: OUTL-BA-OFSC_WACS_ACTIVITY_STAT 01.22.3000 | C31: OUTL-BA-OFSC_WACS_ACTIVITY_STAT | D31: Oracle Utilities OFSC WACS Activity Interim Status | E31: 01.22.3000 | F31: UpdateInterimStatus(i0) | G31: Adapter_Invoke | L31: OUTL-BRT-SOAP-WACS_WACSOFSC | M31: UpdateInterimStatus
A32: OUTL-BA-OFSC_WACS_ASSET_QUERY_01.22.3000.iar.yaml | B32: OUTL-BA-OFSC_WACS_ASSET_QUERY 01.22.3000 | C32: OUTL-BA-OFSC_WACS_ASSET_QUERY | D32: Oracle Utilities OFSC WACS Asset Query | E32: 01.22.3000 | F32: AssetQuery(i0) | G32: Adapter_Invoke | L32: OUTL-BRT-SOAP-WACS_WACSOFSC | M32: AssetQuery
A33: OUTL-BA-OFSC_WACS_ASSET_QUERY_01.22.3000.iar.yaml | B33: OUTL-BA-OFSC_WACS_ASSET_QUERY 01.22.3000 | C33: OUTL-BA-OFSC_WACS_ASSET_QUERY | D33: Oracle Utilities OFSC WACS Asset Query | E33: 01.22.3000 | F33: MainAssetQueryForPickup(i1) | G33: Adapter_Invoke | L33: OUTL-BRT-SOAP-WACS_WACSOFSC | M33: MainAssetQueryForPickup
A34: OUTL-BA-OFSC_WACS_ASSET_QUERY_01.22.3000.iar.yaml | B34: OUTL-BA-OFSC_WACS_ASSET_QUERY 01.22.3000 | C34: OUTL-BA-OFSC_WACS_ASSET_QUERY | D34: Oracle Utilities OFSC WACS Asset Query | E34: 01.22.3000 | F34: GetAssetDetailsForPickup(i2) | G34: Adapter_Invoke | L34: OUTL-BRT-SOAP-WACS_WACSOFSC | M34: GetAssetDetailsForPickup
A35: OUTL-BA-OFSC_WACS_STOREROOM_SYNC_01.22.3000.iar.yaml | B35: OUTL-BA-OFSC_WACS_STOREROOM_SYNC 01.22.3000 | C35: OUTL-BA-OFSC_WACS_STOREROOM_SYNC | D35: Oracle Utilities OFSC WACS Storeroom Sync | E35: 01.22.3000 | F35: GetStoreroomInventoryFromWACS(i1) | G35: Adapter_Invoke | L35: OUTL-BRT-SOAP-WACS_WACSOFSC | M35: GetStoreroomInventoryFromWACS
A36: OUTL-BA-OFSC_WACS_STOREROOM_SYNC_01.22.3000.iar.yaml | B36: OUTL-BA-OFSC_WACS_STOREROOM_SYNC 01.22.3000 | C36: OUTL-BA-OFSC_WACS_STOREROOM_SYNC | D36: Oracle Utilities OFSC WACS Storeroom Sync | E36: 01.22.3000 | F36: resourceinventorybulk(i3) | G36: Adapter_Invoke | K36: /ofscCore/v1/resources/custom-actions/bulkUpdateInventories | L36: OUTL-BRT-REST-OFSC_WACSOFSC | M36: resourceinventorybulk
A37: OUTL-BA-OFSC_WACS_STOREROOM_SYNC_01.22.3000.iar.yaml | B37: OUTL-BA-OFSC_WACS_STOREROOM_SYNC 01.22.3000 | C37: OUTL-BA-OFSC_WACS_STOREROOM_SYNC | D37: Oracle Utilities OFSC WACS Storeroom Sync | E37: 01.22.3000 | F37: getResourceInventories(i4) | G37: Adapter_Invoke | K37: https://tsgt.fs.ocs.oraclecloud.com/rest/ofscCore/v1/resources/{resourceId}/inventories | L37: OUTL-BRT-APP-OFSC_WACSOFSC | M37: getResourceInventories
A38: OUTL-BA-OFSC_WACS_STOREROOM_SYNC_01.22.3000.iar.yaml | B38: OUTL-BA-OFSC_WACS_STOREROOM_SYNC 01.22.3000 | C38: OUTL-BA-OFSC_WACS_STOREROOM_SYNC | D38: Oracle Utilities OFSC WACS Storeroom Sync | E38: 01.22.3000 | F38: bulkupdateinventories(i5) | G38: Adapter_Invoke | K38: /ofscCore/v1/resources/custom-actions/bulkUpdateInventories | L38: OUTL-BRT-REST-OFSC_WACSOFSC | M38: bulkupdateinventories
A39: OUTL-BA-OFSC_WACS_STOREROOM_SYNC_01.22.3000.iar.yaml | B39: OUTL-BA-OFSC_WACS_STOREROOM_SYNC 01.22.3000 | C39: OUTL-BA-OFSC_WACS_STOREROOM_SYNC | D39: Oracle Utilities OFSC WACS Storeroom Sync | E39: 01.22.3000 | F39: UpdateResourceLastSyncDateTime(i0) | G39: Adapter_Invoke | K39: https://tsgt.fs.ocs.oraclecloud.com/rest/ofscCore/v1/resources/{resourceId} | L39: OUTL-BRT-APP-OFSC_WACSOFSC | M39: UpdateResourceLastSyncDateTime
A40: OUTL-BA-OFSC_WACS_WORK_REQ_01.22.3000.iar.yaml | B40: OUTL-BA-OFSC_WACS_WORK_REQ 01.22.3000 | C40: OUTL-BA-OFSC_WACS_WORK_REQ | D40: Oracle Utilities OFSC WACS Work Request | E40: 01.22.3000 | F40: createWorkRequest(i0) | G40: Adapter_Invoke | L40: OUTL-BRT-SOAP-WACS_WACSOFSC | M40: createWorkRequest
A41: OUTL-BA-WACS_OFSC_ADMIN_SYNC_01.22.3000.iar.yaml | B41: OUTL-BA-WACS_OFSC_ADMIN_SYNC 01.22.3000 | C41: OUTL-BA-WACS_OFSC_ADMIN_SYNC | D41: Oracle Utilities WACS OFSC Admin Data Sync | E41: 01.22.3000 | F41: Get_MobileControlData(i0) | G41: Adapter_Invoke | L41: OUTL-BRT-SOAP-WACS_WACSOFSC | M41: Get_MobileControlData
A42: OUTL-BA-WACS_OFSC_ADMIN_SYNC_01.22.3000.iar.yaml | B42: OUTL-BA-WACS_OFSC_ADMIN_SYNC 01.22.3000 | C42: OUTL-BA-WACS_OFSC_ADMIN_SYNC | D42: Oracle Utilities WACS OFSC Admin Data Sync | E42: 01.22.3000 | F42: Get_OFSCWorkSkillConditions(i1) | G42: Adapter_Invoke | K42: /ofscMetadata/v1/workSkillConditions | L42: OUTL-BRT-REST-OFSC_WACSOFSC | M42: Get_OFSCWorkSkillConditions
A43: OUTL-BA-WACS_OFSC_ADMIN_SYNC_01.22.3000.iar.yaml | B43: OUTL-BA-WACS_OFSC_ADMIN_SYNC 01.22.3000 | C43: OUTL-BA-WACS_OFSC_ADMIN_SYNC | D43: Oracle Utilities WACS OFSC Admin Data Sync | E43: 01.22.3000 | F43: PutDowntimeReasonValues(i3) | G43: Adapter_Invoke | K43: /ofscMetadata/v1/properties/wam_downtime_reason/enumerationList | L43: OUTL-BRT-REST-OFSC_WACSOFSC | M43: PutDowntimeReasonValues
A44: OUTL-BA-WACS_OFSC_ADMIN_SYNC_01.22.3000.iar.yaml | B44: OUTL-BA-WACS_OFSC_ADMIN_SYNC 01.22.3000 | C44: OUTL-BA-WACS_OFSC_ADMIN_SYNC | D44: Oracle Utilities WACS OFSC Admin Data Sync | E44: 01.22.3000 | F44: PutMsurementGaugeReasonValues(i12) | G44: Adapter_Invoke | K44: /ofscMetadata/v1/properties/wam_measurement_gauge_reason/enumerationList | L44: OUTL-BRT-REST-OFSC_WACSOFSC | M44: PutMsurementGaugeReasonValues
A45: OUTL-BA-WACS_OFSC_ADMIN_SYNC_01.22.3000.iar.yaml | B45: OUTL-BA-WACS_OFSC_ADMIN_SYNC 01.22.3000 | C45: OUTL-BA-WACS_OFSC_ADMIN_SYNC | D45: Oracle Utilities WACS OFSC Admin Data Sync | E45: 01.22.3000 | F45: PutMsurementMeterReasonValues(i13) | G45: Adapter_Invoke | K45: /ofscMetadata/v1/properties/wam_measurement_meter_reason/enumerationList | L45: OUTL-BRT-REST-OFSC_WACSOFSC | M45: PutMsurementMeterReasonValues
A46: OUTL-BA-WACS_OFSC_ADMIN_SYNC_01.22.3000.iar.yaml | B46: OUTL-BA-WACS_OFSC_ADMIN_SYNC 01.22.3000 | C46: OUTL-BA-WACS_OFSC_ADMIN_SYNC | D46: Oracle Utilities WACS OFSC Admin Data Sync | E46: 01.22.3000 | F46: PutCrewShiftTypeValues(i2) | G46: Adapter_Invoke | K46: /ofscMetadata/v1/properties/wam_crew_shift_type/enumerationList | L46: OUTL-BRT-REST-OFSC_WACSOFSC | M46: PutCrewShiftTypeValues
A47: OUTL-BA-WACS_OFSC_ADMIN_SYNC_01.22.3000.iar.yaml | B47: OUTL-BA-WACS_OFSC_ADMIN_SYNC 01.22.3000 | C47: OUTL-BA-WACS_OFSC_ADMIN_SYNC | D47: Oracle Utilities WACS OFSC Admin Data Sync | E47: 01.22.3000 | F47: PutOvertimeTypeValues(i4) | G47: Adapter_Invoke | K47: /ofscMetadata/v1/properties/wam_overtime_type/enumerationList | L47: OUTL-BRT-REST-OFSC_WACSOFSC | M47: PutOvertimeTypeValues
A48: OUTL-BA-WACS_OFSC_ADMIN_SYNC_01.22.3000.iar.yaml | B48: OUTL-BA-WACS_OFSC_ADMIN_SYNC 01.22.3000 | C48: OUTL-BA-WACS_OFSC_ADMIN_SYNC | D48: Oracle Utilities WACS OFSC Admin Data Sync | E48: 01.22.3000 | F48: PutLaborEarningTypeValues(i5) | G48: Adapter_Invoke | K48: /ofscMetadata/v1/properties/wam_labor_earning_type/enumerationList | L48: OUTL-BRT-REST-OFSC_WACSOFSC | M48: PutLaborEarningTypeValues
A49: OUTL-BA-WACS_OFSC_ADMIN_SYNC_01.22.3000.iar.yaml | B49: OUTL-BA-WACS_OFSC_ADMIN_SYNC 01.22.3000 | C49: OUTL-BA-WACS_OFSC_ADMIN_SYNC | D49: Oracle Utilities WACS OFSC Admin Data Sync | E49: 01.22.3000 | F49: PopulateresourceUOMValues(i9) | G49: Adapter_Invoke | K49: /ofscMetadata/v1/properties/wam_resource_uom/enumerationList | L49: OUTL-BRT-REST-OFSC_WACSOFSC | M49: PopulateresourceUOMValues
A50: OUTL-BA-WACS_OFSC_ADMIN_SYNC_01.22.3000.iar.yaml | B50: OUTL-BA-WACS_OFSC_ADMIN_SYNC 01.22.3000 | C50: OUTL-BA-WACS_OFSC_ADMIN_SYNC | D50: Oracle Utilities WACS OFSC Admin Data Sync | E50: 01.22.3000 | F50: UpdateMaterialUOM(i23) | G50: Adapter_Invoke | K50: /ofscMetadata/v1/properties/wam_material_uom/enumerationList | L50: OUTL-BRT-REST-OFSC_WACSOFSC | M50: UpdateMaterialUOM
A51: OUTL-BA-WACS_OFSC_ADMIN_SYNC_01.22.3000.iar.yaml | B51: OUTL-BA-WACS_OFSC_ADMIN_SYNC 01.22.3000 | C51: OUTL-BA-WACS_OFSC_ADMIN_SYNC | D51: Oracle Utilities WACS OFSC Admin Data Sync | E51: 01.22.3000 | F51: PopulateServiceCategory(i24) | G51: Adapter_Invoke | K51: /ofscMetadata/v1/properties/wam_material_stockItemCategory/enumerationList | L51: OUTL-BRT-REST-OFSC_WACSOFSC | M51: PopulateServiceCategory
A52: OUTL-BA-WACS_OFSC_ADMIN_SYNC_01.22.3000.iar.yaml | B52: OUTL-BA-WACS_OFSC_ADMIN_SYNC 01.22.3000 | C52: OUTL-BA-WACS_OFSC_ADMIN_SYNC | D52: Oracle Utilities WACS OFSC Admin Data Sync | E52: 01.22.3000 | F52: PutLocationTypeValues(i15) | G52: Adapter_Invoke | K52: /ofscMetadata/v1/properties/wam_pickup_location_type/enumerationList | L52: OUTL-BRT-REST-OFSC_WACSOFSC | M52: PutLocationTypeValues
A53: OUTL-BA-WACS_OFSC_ADMIN_SYNC_01.22.3000.iar.yaml | B53: OUTL-BA-WACS_OFSC_ADMIN_SYNC 01.22.3000 | C53: OUTL-BA-WACS_OFSC_ADMIN_SYNC | D53: Oracle Utilities WACS OFSC Admin Data Sync | E53: 01.22.3000 | F53: PutPriorityFlagValues(i16) | G53: Adapter_Invoke | K53: /ofscMetadata/v1/properties/wam_work_priority/enumerationList | L53: OUTL-BRT-REST-OFSC_WACSOFSC | M53: PutPriorityFlagValues
... A64: OUTL-BA-WACS_OFSC_ADMIN_SYNC_01.22.3000.iar.yaml | B64: OUTL-BA-WACS_OFSC_ADMIN_SYNC 01.22.3000 | C64: OUTL-BA-WACS_OFSC_ADMIN_SYNC | D64: Oracle Utilities WACS OFSC Admin Data Sync | E64: 01.22.3000 | F64: PutWorkClass(i22) | G64: Adapter_Invoke | K64: /ofscMetadata/v1/properties/wam_work_class/enumerationList | L64: OUTL-BRT-REST-OFSC_WACSOFSC | M64: PutWorkClass
A65: OUTL-BA-WACS_OFSC_ADMIN_SYNC_01.22.3000.iar.yaml | B65: OUTL-BA-WACS_OFSC_ADMIN_SYNC 01.22.3000 | C65: OUTL-BA-WACS_OFSC_ADMIN_SYNC | D65: Oracle Utilities WACS OFSC Admin Data Sync | E65: 01.22.3000 | F65: GetActivityTypes(i18) | G65: Adapter_Invoke | L65: OUTL-BRT-SOAP-WACS_WACSOFSC | M65: GetActivityTypes
A66: OUTL-BA-WACS_OFSC_ADMIN_SYNC_01.22.3000.iar.yaml | B66: OUTL-BA-WACS_OFSC_ADMIN_SYNC 01.22.3000 | C66: OUTL-BA-WACS_OFSC_ADMIN_SYNC | D66: Oracle Utilities WACS OFSC Admin Data Sync | E66: 01.22.3000 | F66: GetOFSCActitvityTypes(i25) | G66: Adapter_Invoke | K66: /ofscMetadata/v1/activityTypeGroups/{label} | L66: OUTL-BRT-REST-OFSC_WACSOFSC | M66: GetOFSCActitvityTypes
A67: OUTL-BA-WACS_OFSC_ADMIN_SYNC_01.22.3000.iar.yaml | B67: OUTL-BA-WACS_OFSC_ADMIN_SYNC 01.22.3000 | C67: OUTL-BA-WACS_OFSC_ADMIN_SYNC | D67: Oracle Utilities WACS OFSC Admin Data Sync | E67: 01.22.3000 | F67: CreateActivityType(i19) | G67: Adapter_Invoke | K67: /ofscMetadata/v1/activityTypes/{activityType} | L67: OUTL-BRT-REST-OFSC_WACSOFSC | M67: CreateActivityType
A68: OUTL-BA-WACS_OFSC_ADMIN_SYNC_01.22.3000.iar.yaml | B68: OUTL-BA-WACS_OFSC_ADMIN_SYNC 01.22.3000 | C68: OUTL-BA-WACS_OFSC_ADMIN_SYNC | D68: Oracle Utilities WACS OFSC Admin Data Sync | E68: 01.22.3000 | F68: PutActivityTypesPSH(i20) | G68: Adapter_Invoke | K68: /ofscMetadata/v1/properties/wam_actType_psh/enumerationList | L68: OUTL-BRT-REST-OFSC_WACSOFSC | M68: PutActivityTypesPSH
A69: PAYROL_PARALL_TIME_ABSENC_LOAD_01.03.0001.iar.yaml | B69: PAYROL_PARALL_TIME_ABSENC_LOAD 01.03.0001 | C69: PAYROL_PARALL_TIME_ABSENC_LOAD | D69: PAYROLL_PARALLEL_TIME_ABSENCE_LOAD | E69: 01.03.0001 | F69: ListFile(i0) | G69: Adapter_Invoke | L69: TSGTFTP_CONN | M69: ListFile
A70: PAYROL_PARALL_TIME_ABSENC_LOAD_01.03.0001.iar.yaml | B70: PAYROL_PARALL_TIME_ABSENC_LOAD 01.03.0001 | C70: PAYROL_PARALL_TIME_ABSENC_LOAD | D70: PAYROLL_PARALLEL_TIME_ABSENCE_LOAD | E70: 01.03.0001 | F70: Download(i1) | G70: Adapter_Invoke | L70: TSGTFTP_CONN | M70: Download
A71: PAYROL_PARALL_TIME_ABSENC_LOAD_01.03.0001.iar.yaml | B71: PAYROL_PARALL_TIME_ABSENC_LOAD 01.03.0001 | C71: PAYROL_PARALL_TIME_ABSENC_LOAD | D71: PAYROLL_PARALLEL_TIME_ABSENCE_LOAD | E71: 01.03.0001 | F71: GetLegalEmployer(i2) | G71: Adapter_Invoke | K71: /hcmRestApi/resources/11.13.18.05/workers | L71: FUSION_REST_CONN | M71: GetLegalEmployer
A72: PAYROL_PARALL_TIME_ABSENC_LOAD_01.03.0001.iar.yaml | B72: PAYROL_PARALL_TIME_ABSENC_LOAD 01.03.0001 | C72: PAYROL_PARALL_TIME_ABSENC_LOAD | D72: PAYROLL_PARALLEL_TIME_ABSENCE_LOAD | E72: 01.03.0001 | F72: CreateAbsenceTransaction(i3) | G72: Adapter_Invoke | K72: /hcmRestApi/resources/latest/absences | L72: FUSION_REST_CONN | M72: CreateAbsenceTransaction
A73: PAYROL_PARALL_TIME_ABSENC_LOAD_01.03.0001.iar.yaml | B73: PAYROL_PARALL_TIME_ABSENC_LOAD 01.03.0001 | C73: PAYROL_PARALL_TIME_ABSENC_LOAD | D73: PAYROLL_PARALLEL_TIME_ABSENCE_LOAD | E73: 01.03.0001 | F73: GetProjectId(i6) | G73: Adapter_Invoke | K73: /fscmRestApi/resources/latest/projects | L73: FUSION_REST_CONN | M73: GetProjectId
A74: PAYROL_PARALL_TIME_ABSENC_LOAD_01.03.0001.iar.yaml | B74: PAYROL_PARALL_TIME_ABSENC_LOAD 01.03.0001 | C74: PAYROL_PARALL_TIME_ABSENC_LOAD | D74: PAYROLL_PARALLEL_TIME_ABSENCE_LOAD | E74: 01.03.0001 | F74: GetTaskId(i7) | G74: Adapter_Invoke | K74: /fscmRestApi/resources/latest/projects/{ProjectId}/child/Tasks | L74: FUSION_REST_CONN | M74: GetTaskId
A75: PAYROL_PARALL_TIME_ABSENC_LOAD_01.03.0001.iar.yaml | B75: PAYROL_PARALL_TIME_ABSENC_LOAD 01.03.0001 | C75: PAYROL_PARALL_TIME_ABSENC_LOAD | D75: PAYROLL_PARALLEL_TIME_ABSENCE_LOAD | E75: 01.03.0001 | F75: ExpenditureType(i8) | G75: Adapter_Invoke | K75: /fscmRestApi/resources/latest/expenditureTypes | L75: FUSION_REST_CONN | M75: ExpenditureType
A76: PAYROL_PARALL_TIME_ABSENC_LOAD_01.03.0001.iar.yaml | B76: PAYROL_PARALL_TIME_ABSENC_LOAD 01.03.0001 | C76: PAYROL_PARALL_TIME_ABSENC_LOAD | D76: PAYROLL_PARALLEL_TIME_ABSENCE_LOAD | E76: 01.03.0001 | F76: GetGradeStepId(i9) | G76: Adapter_Invoke | K76: /hcmRestApi/resources/latest/grades | L76: FUSION_REST_CONN | M76: GetGradeStepId
A77: PAYROL_PARALL_TIME_ABSENC_LOAD_01.03.0001.iar.yaml | B77: PAYROL_PARALL_TIME_ABSENC_LOAD 01.03.0001 | C77: PAYROL_PARALL_TIME_ABSENC_LOAD | D77: PAYROLL_PARALLEL_TIME_ABSENCE_LOAD | E77: 01.03.0001 | F77: GradeStepIdForHoliday(i10) | G77: Adapter_Invoke | K77: /hcmRestApi/resources/latest/grades | L77: FUSION_REST_CONN | M77: GradeStepIdForHoliday
A78: PAYROL_PARALL_TIME_ABSENC_LOAD_01.03.0001.iar.yaml | B78: PAYROL_PARALL_TIME_ABSENC_LOAD 01.03.0001 | C78: PAYROL_PARALL_TIME_ABSENC_LOAD | D78: PAYROLL_PARALLEL_TIME_ABSENCE_LOAD | E78: 01.03.0001 | F78: CreateTimeEventRequests(i5) | G78: Adapter_Invoke | K78: /hcmRestApi/resources/latest/timeEventRequests | L78: FUSION_REST_CONN | M78: CreateTimeEventRequests
A79: PAYROL_PARALL_TIME_ABSENC_LOAD_01.03.0001.iar.yaml | B79: PAYROL_PARALL_TIME_ABSENC_LOAD 01.03.0001 | C79: PAYROL_PARALL_TIME_ABSENC_LOAD | D79: PAYROLL_PARALLEL_TIME_ABSENCE_LOAD | E79: 01.03.0001 | F79: GeneratOutput(i4) | G79: Adapter_Invoke | L79: TSGTFTP_CONN | M79: GeneratOutput
A80: TSGTADAPT2ARINV_INTGSERVIC_IB_01.00.0000.iar.yaml | B80: TSGTADAPT2ARINV_INTGSERVIC_IB 01.00.0000 | C80: TSGTADAPT2ARINV_INTGSERVIC_IB | D80: TSGTAdapt2ARInvoice_IntgService_IB | E80: 01.00.0000 | F80: GetMetadataFromBO(i3) | G80: Adapter_Invoke | K80: /FWKOUTBOUNDINTGMETADATA | L80: TSGTRESTVBCSBO_CONN | M80: GetMetadataFromBO
A81: TSGTADAPT2ARINV_INTGSERVIC_IB_01.00.0000.iar.yaml | B81: TSGTADAPT2ARINV_INTGSERVIC_IB 01.00.0000 | C81: TSGTADAPT2ARINV_INTGSERVIC_IB | D81: TSGTAdapt2ARInvoice_IntgService_IB | E81: 01.00.0000 | F81: InvokeCommonLauncher(i0) | G81: IntegrationAction | H81: TSGTCMNLAUNCHERF_SERVICE | I81: 01.00.0000 | J81: TSGTCmnLauncherFwk_Service | K81: /invokeLauncher | L81: PRESEEDED_COLLOCATED_CONN_1741 | M81: InvokeCommonLauncher
A82: TSGTADAPT2ARINV_INTGSERVIC_IB_01.00.0000.iar.yaml | B82: TSGTADAPT2ARINV_INTGSERVIC_IB 01.00.0000 | C82: TSGTADAPT2ARINV_INTGSERVIC_IB | D82: TSGTAdapt2ARInvoice_IntgService_IB | E82: 01.00.0000 | F82: SendNotification(i1) | G82: IntegrationAction | H82: TSGTCMNNOTIFICAT_SERVICE | I82: 01.00.0000 | J82: TSGTCmnNotificationFwk_Service | K82: /Notify | L82: PRESEEDED_COLLOCATED_CONN_1741 | M82: SendNotification
A83: TSGTAUDITINGPROC_SERVICE_01.04.0001.iar.yaml | B83: TSGTAUDITINGPROC_SERVICE 01.04.0001 | C83: TSGTAUDITINGPROC_SERVICE | D83: TSGTAuditingProcess_Service | E83: 01.04.0001 | F83: GetConfigs(i0) | G83: IntegrationAction | H83: TSGTGETCONFIGS_SERVICE | I83: 01.02.0000 | J83: TSGTGetConfigs_Service | K83: /configs | L83: PRESEEDED_COLLOCATED_CONN_1741 | M83: GetConfigs
A84: TSGTAUDITINGPROC_SERVICE_01.04.0001.iar.yaml | B84: TSGTAUDITINGPROC_SERVICE 01.04.0001 | C84: TSGTAUDITINGPROC_SERVICE | D84: TSGTAuditingProcess_Service | E84: 01.04.0001 | F84: AttechmentFile(i1) | G84: Adapter_Invoke | L84: TSGTFTP_CONN | M84: AttechmentFile
A85: TSGTAUDITINGPROC_SERVICE_01.04.0001.iar.yaml | B85: TSGTAUDITINGPROC_SERVICE 01.04.0001 | C85: TSGTAUDITINGPROC_SERVICE | D85: TSGTAuditingProcess_Service | E85: 01.04.0001 | F85: attachmentDowonload(i2) | G85: Adapter_Invoke | L85: TSGTFTP_CONN | M85: attachmentDowonload
A86: TSGTAZUREADEMPLOYEESOUTBOUNDHCM_02.05.0003.iar.yaml | B86: TSGTAZUREADEMPLOYEESOUTBOUNDHCM 02.05.0003 | C86: TSGTAZUREADEMPLOYEESOUTBOUNDHCM | D86: TSGTAzureADEmployeesOutboundHCM | E86: 02.05.0003 | F86: GetConfigs(i0) | G86: RESTToOIC | H86: TSGTGETCONFIGS_SERVICE | I86: 1 | J86: TSGTGetConfigs_Service | K86: /api/integration/v1/flows/rest/TSGTGETCONFIGS_SERVICE/1.0/configs | L86: TSGTRESTOICINVOK_CONN | M86: GetConfigs
A87: TSGTAZUREADEMPLOYEESOUTBOUNDHCM_02.05.0003.iar.yaml | B87: TSGTAZUREADEMPLOYEESOUTBOUNDHCM 02.05.0003 | C87: TSGTAZUREADEMPLOYEESOUTBOUNDHCM | D87: TSGTAzureADEmployeesOutboundHCM | E87: 02.05.0003 | F87: WriteHeadersTraceFile(i12) | G87: Adapter_Invoke | L87: TSGTFTP_CONN | M87: WriteHeadersTraceFile
A88: TSGTAZUREADEMPLOYEESOUTBOUNDHCM_02.05.0003.iar.yaml | B88: TSGTAZUREADEMPLOYEESOUTBOUNDHCM 02.05.0003 | C88: TSGTAZUREADEMPLOYEESOUTBOUNDHCM | D88: TSGTAzureADEmployeesOutboundHCM | E88: 02.05.0003 | F88: GetNextDelta(i2) | G88: Adapter_Invoke | K88: /users/delta | L88: TSGTREST2MSGRAPH_CONN | M88: GetNextDelta
A89: TSGTAZUREADEMPLOYEESOUTBOUNDHCM_02.05.0003.iar.yaml | B89: TSGTAZUREADEMPLOYEESOUTBOUNDHCM 02.05.0003 | C89: TSGTAZUREADEMPLOYEESOUTBOUNDHCM | D89: TSGTAzureADEmployeesOutboundHCM | E89: 02.05.0003 | F89: WriteWorkPhone(i11) | G89: Adapter_Invoke | L89: TSGTFTP_CONN | M89: WriteWorkPhone
A90: TSGTAZUREADEMPLOYEESOUTBOUNDHCM_02.05.0003.iar.yaml | B90: TSGTAZUREADEMPLOYEESOUTBOUNDHCM 02.05.0003 | C90: TSGTAZUREADEMPLOYEESOUTBOUNDHCM | D90: TSGTAzureADEmployeesOutboundHCM | E90: 02.05.0003 | F90: GetEmployee(i3) | G90: Adapter_Invoke | K90: /workers | L90: TSGTRESTHCMCLOUD_CONN | M90: GetEmployee
A91: TSGTAZUREADEMPLOYEESOUTBOUNDHCM_02.05.0003.iar.yaml | B91: TSGTAZUREADEMPLOYEESOUTBOUNDHCM 02.05.0003 | C91: TSGTAZUREADEMPLOYEESOUTBOUNDHCM | D91: TSGTAzureADEmployeesOutboundHCM | E91: 02.05.0003 | F91: AddWorkPhone(i4) | G91: Adapter_Invoke | K91: / | L91: TSGTRESTHCMCLOUD_CONN | M91: AddWorkPhone
A92: TSGTAZUREADEMPLOYEESOUTBOUNDHCM_02.05.0003.iar.yaml | B92: TSGTAZUREADEMPLOYEESOUTBOUNDHCM 02.05.0003 | C92: TSGTAZUREADEMPLOYEESOUTBOUNDHCM | D92: TSGTAzureADEmployeesOutboundHCM | E92: 02.05.0003 | F92: UpdateWorkPhone(i5) | G92: Adapter_Invoke | K92: / | L92: TSGTRESTHCMCLOUD_CONN | M92: UpdateWorkPhone
A93: TSGTAZUREADEMPLOYEESOUTBOUNDHCM_02.05.0003.iar.yaml | B93: TSGTAZUREADEMPLOYEESOUTBOUNDHCM 02.05.0003 | C93: TSGTAZUREADEMPLOYEESOUTBOUNDHCM | D93: TSGTAzureADEmployeesOutboundHCM | E93: 02.05.0003 | F93: AddWorkMobile(i13) | G93: Adapter_Invoke | K93: / | L93: TSGTRESTHCMCLOUD_CONN | M93: AddWorkMobile
A94: TSGTAZUREADEMPLOYEESOUTBOUNDHCM_02.05.0003.iar.yaml | B94: TSGTAZUREADEMPLOYEESOUTBOUNDHCM 02.05.0003 | C94: TSGTAZUREADEMPLOYEESOUTBOUNDHCM | D94: TSGTAzureADEmployeesOutboundHCM | E94: 02.05.0003 | F94: UpdateWorkMobile(i14) | G94: Adapter_Invoke | K94: / | L94: TSGTRESTHCMCLOUD_CONN | M94: UpdateWorkMobile
A95: TSGTAZUREADEMPLOYEESOUTBOUNDHCM_02.05.0003.iar.yaml | B95: TSGTAZUREADEMPLOYEESOUTBOUNDHCM 02.05.0003 | C95: TSGTAZUREADEMPLOYEESOUTBOUNDHCM | D95: TSGTAzureADEmployeesOutboundHCM | E95: 02.05.0003 | F95: SaveError(i9) | G95: Adapter_Invoke | L95: TSGTFTP_CONN | M95: SaveError
A96: TSGTAZUREADEMPLOYEESOUTBOUNDHCM_02.05.0003.iar.yaml | B96: TSGTAZUREADEMPLOYEESOUTBOUNDHCM 02.05.0003 | C96: TSGTAZUREADEMPLOYEESOUTBOUNDHCM | D96: TSGTAzureADEmployeesOutboundHCM | E96: 02.05.0003 | F96: PublishAuditing4Batch(i8) | G96: IntegrationAction | H96: TSGTPUBLISHAUDIT_SERVICE | I96: 01.00.0000 | J96: TSGTPublishAuditing_Service | K96: /auditing | L96: PRESEEDED_COLLOCATED_CONN_1741 | M96: PublishAuditing4Batch
A97: TSGTAZUREADEMPLOYEESOUTBOUNDHCM_02.05.0003.iar.yaml | B97: TSGTAZUREADEMPLOYEESOUTBOUNDHCM 02.05.0003 | C97: TSGTAZUREADEMPLOYEESOUTBOUNDHCM | D97: TSGTAzureADEmployeesOutboundHCM | E97: 02.05.0003 | F97: UpdateConfigs(i1) | G97: RESTToOIC | H97: TSGTUPDATECONFIG_SERVICE | I97: 1 | J97: TSGTUpdateConfigs_Service | K97: /api/integration/v1/flows/rest/TSGTUPDATECONFIG_SERVICE/1.0/configs | L97: TSGTRESTOICINVOK_CONN | M97: UpdateConfigs
A98: TSGTAZUREADEMPLOYEESOUTBOUNDHCM_02.05.0003.iar.yaml | B98: TSGTAZUREADEMPLOYEESOUTBOUNDHCM 02.05.0003 | C98: TSGTAZUREADEMPLOYEESOUTBOUNDHCM | D98: TSGTAzureADEmployeesOutboundHCM | E98: 02.05.0003 | F98: PublishAuditingFault(i10) | G98: IntegrationAction | H98: TSGTPUBLISHAUDIT_SERVICE | I98: 01.00.0000 | J98: TSGTPublishAuditing_Service | K98: /auditing | L98: PRESEEDED_COLLOCATED_CONN_1741 | M98: PublishAuditingFault
A99: TSGTAZUREADEMPLOYEESOUTBOUNDHCM_02.05.0003.iar.yaml | B99: TSGTAZUREADEMPLOYEESOUTBOUNDHCM 02.05.0003 | C99: TSGTAZUREADEMPLOYEESOUTBOUNDHCM | D99: TSGTAzureADEmployeesOutboundHCM | E99: 02.05.0003 | F99: ReadErrors(i7) | G99: Adapter_Invoke | L99: TSGTFTP_CONN | M99: ReadErrors
A100: TSGTAZUREADEMPLOYEESOUTBOUNDHCM_02.05.0003.iar.yaml | B100: TSGTAZUREADEMPLOYEESOUTBOUNDHCM 02.05.0003 | C100: TSGTAZUREADEMPLOYEESOUTBOUNDHCM | D100: TSGTAzureADEmployeesOutboundHCM | E100: 02.05.0003 | F100: NotifyErrors(i15) | G100: IntegrationAction | H100: TSGTPUBLISHAUDIT_SERVICE | I100: 01.00.0000 | J100: TSGTPublishAuditing_Service | K100: /auditing | L100: PRESEEDED_COLLOCATED_CONN_1741 | M100: NotifyErrors
A101: TSGTAZUREADEMPLOYEESOUTBOUNDHCM_02.05.0003.iar.yaml | B101: TSGTAZUREADEMPLOYEESOUTBOUNDHCM 02.05.0003 | C101: TSGTAZUREADEMPLOYEESOUTBOUNDHCM | D101: TSGTAzureADEmployeesOutboundHCM | E101: 02.05.0003 | F101: PublishAuditing(i6) | G101: RESTToOIC | H101: TSGTPUBLISHAUDIT_SERVICE | I101: 1 | J101: TSGTPublishAuditing_Service | K101: /api/integration/v1/flows/rest/TSGTPUBLISHAUDIT_SERVICE/1.0/auditing | L101: TSGTRESTOICINVOK_CONN | M101: PublishAuditing
A102: TSGTCMNAPPCOMPOS_SERVICE_01.00.0000.iar.yaml | B102: TSGTCMNAPPCOMPOS_SERVICE 01.00.0000 | C102: TSGTCMNAPPCOMPOS_SERVICE | D102: TSGTCmnAppComposerObjUpdate_Service | E102: 01.00.0000 | F102: GetFieldDetails(i0) | G102: Adapter_Invoke | K102: /fscmRestApi/resources/latest/{CustomObject} | L102: TSGTRESTERPCLOUD_CONN | M102: GetFieldDetails
A103: TSGTCMNAPPCOMPOS_SERVICE_01.00.0000.iar.yaml | B103: TSGTCMNAPPCOMPOS_SERVICE 01.00.0000 | C103: TSGTCMNAPPCOMPOS_SERVICE | D103: TSGTCmnAppComposerObjUpdate_Service | E103: 01.00.0000 | F103: UpdateRESTAPI(i1) | G103: Adapter_Invoke | K103: /fscmRestApi/resources/latest | L103: TSGTRESTERPCLOUD_CONN | M103: UpdateRESTAPI
A104: TSGTCMNARERPORCH_SERVICE_01.00.0000.iar.yaml | B104: TSGTCMNARERPORCH_SERVICE 01.00.0000 | C104: TSGTCMNARERPORCH_SERVICE | D104: TSGTCmnARErpOrchestratorIbFwk_Service | E104: 01.00.0000 | F104: InvokeLoggerService-Initiation(i7) | G104: IntegrationAction | H104: TSGTCMNUPSERTINS_SERVICE | I104: 01.00.0000 | J104: TSGTCmnUpsertInstanceTransaction_Service | K104: /UpsertInstanceTransaction | L104: PRESEEDED_COLLOCATED_CONN_1741 | M104: InvokeLoggerService-Initiation
A105: TSGTCMNARERPORCH_SERVICE_01.00.0000.iar.yaml | B105: TSGTCMNARERPORCH_SERVICE 01.00.0000 | C105: TSGTCMNARERPORCH_SERVICE | D105: TSGTCmnARErpOrchestratorIbFwk_Service | E105: 01.00.0000 | F105: GetInstanceDtls(i13) | G105: Adapter_Invoke | K105: /Instances | L105: TSGTRESTVBCSBO_CONN | M105: GetInstanceDtls
A106: TSGTCMNARERPORCH_SERVICE_01.00.0000.iar.yaml | B106: TSGTCMNARERPORCH_SERVICE 01.00.0000 | C106: TSGTCMNARERPORCH_SERVICE | D106: TSGTCmnARErpOrchestratorIbFwk_Service | E106: 01.00.0000 | F106: GetMetadataInfo(i1) | G106: Adapter_Invoke | K106: /FWKINBOUNDINTGMETADATA | L106: TSGTRESTVBCSBO_CONN | M106: GetMetadataInfo
A107: TSGTCMNARERPORCH_SERVICE_01.00.0000.iar.yaml | B107: TSGTCMNARERPORCH_SERVICE 01.00.0000 | C107: TSGTCMNARERPORCH_SERVICE | D107: TSGTCmnARErpOrchestratorIbFwk_Service | E107: 01.00.0000 | F107: GetBusinessUnitIdentifier(i21) | G107: Adapter_Invoke | L107: TSGTATPCLOUDDB_CONN | M107: GetBusinessUnitIdentifier
A108: TSGTCMNARERPORCH_SERVICE_01.00.0000.iar.yaml | B108: TSGTCMNARERPORCH_SERVICE 01.00.0000 | C108: TSGTCMNARERPORCH_SERVICE | D108: TSGTCmnARErpOrchestratorIbFwk_Service | E108: 01.00.0000 | F108: GetARInterfaceLinesData(i19) | G108: Adapter_Invoke | L108: TSGTATPCLOUDDB_CONN | M108: GetARInterfaceLinesData
A109: TSGTCMNARERPORCH_SERVICE_01.00.0000.iar.yaml | B109: TSGTCMNARERPORCH_SERVICE 01.00.0000 | C109: TSGTCMNARERPORCH_SERVICE | D109: TSGTCmnARErpOrchestratorIbFwk_Service | E109: 01.00.0000 | F109: GetARInterfaceDistributionsData(i20) | G109: Adapter_Invoke | L109: TSGTATPCLOUDDB_CONN | M109: GetARInterfaceDistributionsData
A110: TSGTCMNARERPORCH_SERVICE_01.00.0000.iar.yaml | B110: TSGTCMNARERPORCH_SERVICE 01.00.0000 | C110: TSGTCMNARERPORCH_SERVICE | D110: TSGTCmnARErpOrchestratorIbFwk_Service | E110: 01.00.0000 | F110: MoveFBDIZipFileToEnrichedBucket(i16) | G110: Adapter_Invoke | K110: /n/{namespace}/b/{bucketName}/o/{objectName} | L110: TSGTOBJECTSTORAG_CONN | M110: MoveFBDIZipFileToEnrichedBucket
...
